{
  "version": 2,
  "extractor": "papercropper",
  "tables": [
    {
      "url": "assets/tables/arxiv/2606.06493v3/table-001.webp",
      "caption": "",
      "page": 0,
      "index": 1,
      "width": 1452,
      "height": 339,
      "label": "Table"
    },
    {
      "url": "assets/tables/arxiv/2606.06493v3/table-002.webp",
      "caption": "",
      "page": 0,
      "index": 2,
      "width": 714,
      "height": 307,
      "label": "Table"
    },
    {
      "url": "assets/tables/arxiv/2606.06493v3/table-003.webp",
      "caption": "",
      "page": 0,
      "index": 3,
      "width": 716,
      "height": 306,
      "label": "Table"
    },
    {
      "url": "assets/tables/arxiv/2606.06493v3/table-004.webp",
      "caption": "",
      "page": 0,
      "index": 4,
      "width": 1431,
      "height": 999,
      "label": "Table"
    },
    {
      "url": "assets/tables/arxiv/2606.06493v3/table-005.webp",
      "caption": "",
      "page": 0,
      "index": 5,
      "width": 1428,
      "height": 516,
      "label": "Table"
    },
    {
      "url": "assets/tables/arxiv/2606.06493v3/table-006.webp",
      "caption": "",
      "page": 0,
      "index": 6,
      "width": 1428,
      "height": 204,
      "label": "Table"
    },
    {
      "url": "assets/tables/arxiv/2606.06493v3/table-007.webp",
      "caption": "",
      "page": 0,
      "index": 7,
      "width": 1430,
      "height": 917,
      "label": "Table"
    },
    {
      "url": "assets/tables/arxiv/2606.06493v3/table-008.webp",
      "caption": "",
      "page": 0,
      "index": 8,
      "width": 1358,
      "height": 270,
      "label": "Table"
    },
    {
      "url": "assets/tables/arxiv/2606.06493v3/table-009.webp",
      "caption": "",
      "page": 0,
      "index": 9,
      "width": 1427,
      "height": 638,
      "label": "Table"
    },
    {
      "url": "assets/tables/arxiv/2606.06493v3/table-010.webp",
      "caption": "",
      "page": 0,
      "index": 10,
      "width": 1353,
      "height": 1143,
      "label": "Table"
    },
    {
      "url": "assets/tables/arxiv/2606.06493v3/table-011.webp",
      "caption": "",
      "page": 0,
      "index": 11,
      "width": 1415,
      "height": 815,
      "label": "Table"
    },
    {
      "url": "assets/tables/arxiv/2606.06493v3/table-012.webp",
      "caption": "",
      "page": 0,
      "index": 12,
      "width": 1409,
      "height": 132,
      "label": "Table"
    },
    {
      "url": "assets/tables/arxiv/2606.06493v3/table-013.webp",
      "caption": "",
      "page": 0,
      "index": 13,
      "width": 1346,
      "height": 622,
      "label": "Table"
    },
    {
      "url": "assets/tables/arxiv/2606.06493v3/table-014.webp",
      "caption": "",
      "page": 0,
      "index": 14,
      "width": 1416,
      "height": 711,
      "label": "Table"
    },
    {
      "url": "assets/tables/arxiv/2606.06493v3/table-015.webp",
      "caption": "",
      "page": 0,
      "index": 15,
      "width": 1392,
      "height": 870,
      "label": "Table"
    }
  ]
}